es2csv_cli/__init__.py
es2csv_cli/export.py
es2csv_cli/job.py
es2csv_cli/utils/__init__.py
es2csv_cli/utils/async_worker.py
es2csv_cli/utils/csv_util.py
es2csv_cli/utils/file.py
parallel_es2csv-0.1.10.data/scripts/parallel-es2csv
parallel_es2csv-0.1.10.dist-info/METADATA
parallel_es2csv-0.1.10.dist-info/RECORD
parallel_es2csv-0.1.10.dist-info/WHEEL
parallel_es2csv-0.1.10.dist-info/top_level.txt
