Metadata-Version: 2.1
Name: parallel-es2csv
Version: 0.1.10
Summary: A CLI client for exporting elasticsearch data to csv
Home-page: https://github.com/therako/parallel-es2csv
Author: Arunkumar Ramanathan
Author-email: rako.aka.arun@gmail.com
License: MIT License
Platform: UNKNOWN
Classifier: License :: OSI Approved :: MIT License
Classifier: Development Status :: 3 - Alpha
Classifier: Operating System :: OS Independent
Classifier: Programming Language :: Python
Classifier: Programming Language :: Python :: 2
Classifier: Programming Language :: Python :: 2.7
Requires-Dist: elasticsearch (<7.0.0,>=6.0.0)
Requires-Dist: elasticsearch-dsl (<7.0.0,>=6.0.0)
Requires-Dist: tqdm (==4.19.8)
Requires-Dist: futures; python_version == "2.7"
